dadeschools.py
dadeschools-1.6.dist-info/LICENSE
dadeschools-1.6.dist-info/WHEEL
dadeschools-1.6.dist-info/entry_points.txt
dadeschools-1.6.dist-info/METADATA
dadeschools-1.6.dist-info/RECORD
